{
  "title": "Easy crossword Sampler",
  "author": "By Scott Curran/Ed. by Avalonian",
  "clues": {
    "across": [
      "1. Orchestra instrument",
      "5. Box",
      "9. Woeful exclamation",
      "13. Beach bed",
      "17. Albacore",
      "18. Rent",
      "19. Pretzel seasoning",
      "20. Not aweather",
      "21. Enlarges",
      "23. Bogota resident",
      "25. Unfruitful",
      "26. __ and cons",
      "28. Insignificant",
      "29. Wrath",
      "30. Honk",
      "31. Adore",
      "32. Public outburst",
      "35. Ebb",
      "36. New versions",
      "40. Yearn",
      "41. Do origami",
      "42. Church sections",
      "43. __ \"King\" Cole",
      "44. Horse's morsel",
      "45. Nude",
      "46. Provide food",
      "47. Turner of Hollywood",
      "48. Appease",
      "50. Prank",
      "51. In the future",
      "52. Zilch",
      "53. Stared dumbfoundedly",
      "54. Fashionable",
      "55. \"Fibber __ and Molly\"",
      "57. Three-dimensional figures",
      "58. Competition",
      "61. \"__ Lang Syne\"",
      "62. Slaves",
      "63. Drill",
      "64. Cattle cry",
      "65. Honshu city",
      "66. Consisting of two",
      "67. Faxed",
      "68. Farm structure",
      "69. Generosity",
      "71. __-in-one",
      "72. Gluelike",
      "73. Ceremony",
      "74. Beef",
      "75. Simple melody",
      "76. Royal residence",
      "79. Boxer Max",
      "80. Savings __",
      "84. Of the outer skin",
      "86. Magician",
      "88. Sage",
      "89. Facility",
      "90. Steak preference",
      "91. Roof overhang",
      "92. Weakens",
      "93. Eosin and aniline, e.g.",
      "94. Hurried",
      "95. \"__ All Laughed\""
    ],
    "down": [
      "1. Redding or Skinner",
      "2. Batter's ploy",
      "3. Formerly",
      "4. Jewelry item",
      "5. Not fresh",
      "6. Sit",
      "7. Exist",
      "8. Answer",
      "9. Tie type",
      "10. Asian country",
      "11. Everything",
      "12. Journey interruption",
      "13. Fur coats",
      "14. Touched down",
      "15. Approach",
      "16. Gainsay",
      "22. Ireland, formerly",
      "24. Song thrush",
      "27. Caviar",
      "30. Story",
      "31. Operating handle",
      "32. Unappetizing food",
      "33. \"__ Miner's Daughter\"",
      "34. Something which confuses",
      "35. Donned",
      "36. Assessed",
      "37. Curses",
      "38. Alley",
      "39. Constellation part",
      "41. Destiny",
      "42. Scruffs",
      "45. Downfall",
      "46. Cod and May",
      "47. Go the distance",
      "49. Admitting both men and women",
      "50. Thick wire",
      "51. Isolated",
      "53. Deceit",
      "54. Sweet wine",
      "55. Heavy hammer",
      "56. Havana's locale",
      "57. Thicket",
      "58. Ice cream holder",
      "59. Ilk",
      "60. Danza or Bennett",
      "62. Gathered, as courage",
      "63. Alternative to suspenders",
      "66. Thaw",
      "67. Eagles and airplanes, e.g.",
      "68. British title of honor",
      "70. Marks, as exams",
      "71. \"__ Haw\"",
      "72. Type size",
      "74. Men",
      "75. Was sore",
      "76. Church seats",
      "77. Capital of Western Samoa",
      "78. Speech flaw",
      "79. Headquarters",
      "80. Land unit",
      "81. Great Salt Lake locale",
      "82. Granular snow",
      "83. Deuce topper",
      "85. Spring month",
      "87. Snooze"
    ]
  },
  "grid": [
    "O",
    "B",
    "O",
    "E",
    ".",
    "S",
    "P",
    "A",
    "R",
    ".",
    "A",
    "L",
    "A",
    "S",
    ".",
    "S",
    "A",
    "N",
    "D",
    "T",
    "U",
    "N",
    "A",
    ".",
    "T",
    "O",
    "R",
    "E",
    ".",
    "S",
    "A",
    "L",
    "T",
    ".",
    "A",
    "L",
    "E",
    "E",
    "I",
    "N",
    "C",
    "R",
    "E",
    "A",
    "S",
    "E",
    "S",
    ".",
    "C",
    "O",
    "L",
    "O",
    "M",
    "B",
    "I",
    "A",
    "N",
    "S",
    "T",
    "E",
    "R",
    "I",
    "L",
    "E",
    ".",
    "P",
    "R",
    "O",
    "S",
    ".",
    "P",
    "A",
    "L",
    "T",
    "R",
    "Y",
    ".",
    ".",
    ".",
    "I",
    "R",
    "E",
    ".",
    "T",
    "O",
    "O",
    "T",
    ".",
    "L",
    "O",
    "V",
    "E",
    ".",
    ".",
    ".",
    "S",
    "C",
    "E",
    "N",
    "E",
    ".",
    "W",
    "A",
    "N",
    "E",
    ".",
    "R",
    "E",
    "V",
    "I",
    "S",
    "A",
    "L",
    "S",
    "L",
    "O",
    "N",
    "G",
    ".",
    "F",
    "O",
    "L",
    "D",
    ".",
    "N",
    "A",
    "V",
    "E",
    "S",
    ".",
    "N",
    "A",
    "T",
    "O",
    "A",
    "T",
    ".",
    "B",
    "A",
    "R",
    "E",
    ".",
    "C",
    "A",
    "T",
    "E",
    "R",
    ".",
    "L",
    "A",
    "N",
    "A",
    "P",
    "L",
    "A",
    "C",
    "A",
    "T",
    "E",
    ".",
    "C",
    "A",
    "P",
    "E",
    "R",
    ".",
    "L",
    "A",
    "T",
    "E",
    "R",
    ".",
    ".",
    "N",
    "O",
    "N",
    "E",
    ".",
    "G",
    "A",
    "P",
    "E",
    "D",
    ".",
    "P",
    "O",
    "S",
    "H",
    ".",
    ".",
    "M",
    "C",
    "G",
    "E",
    "E",
    ".",
    "C",
    "U",
    "B",
    "E",
    "S",
    ".",
    "C",
    "O",
    "N",
    "T",
    "E",
    "S",
    "T",
    "A",
    "U",
    "L",
    "D",
    ".",
    "M",
    "O",
    "I",
    "L",
    "S",
    ".",
    "B",
    "O",
    "R",
    "E",
    ".",
    "M",
    "O",
    "O",
    "U",
    "B",
    "E",
    ".",
    "D",
    "U",
    "P",
    "L",
    "E",
    ".",
    "S",
    "E",
    "N",
    "T",
    ".",
    "B",
    "A",
    "R",
    "N",
    "L",
    "A",
    "R",
    "G",
    "E",
    "S",
    "S",
    "E",
    ".",
    "H",
    "O",
    "L",
    "E",
    ".",
    "P",
    "A",
    "S",
    "T",
    "Y",
    ".",
    ".",
    ".",
    "R",
    "I",
    "T",
    "E",
    ".",
    "M",
    "E",
    "A",
    "T",
    ".",
    "A",
    "I",
    "R",
    ".",
    ".",
    ".",
    "P",
    "A",
    "L",
    "A",
    "C",
    "E",
    ".",
    "B",
    "A",
    "E",
    "R",
    ".",
    "A",
    "C",
    "C",
    "O",
    "U",
    "N",
    "T",
    "E",
    "P",
    "I",
    "D",
    "E",
    "R",
    "M",
    "A",
    "L",
    ".",
    "E",
    "N",
    "C",
    "H",
    "A",
    "N",
    "T",
    "E",
    "R",
    "W",
    "I",
    "S",
    "E",
    ".",
    "E",
    "A",
    "S",
    "E",
    ".",
    "R",
    "A",
    "R",
    "E",
    ".",
    "E",
    "A",
    "V",
    "E",
    "S",
    "A",
    "P",
    "S",
    ".",
    "D",
    "Y",
    "E",
    "S",
    ".",
    "S",
    "P",
    "E",
    "D",
    ".",
    "T",
    "H",
    "E",
    "Y"
  ],
  "gridNums": [
    1,
    2,
    3,
    4,
    0,
    5,
    6,
    7,
    8,
    0,
    9,
    10,
    11,
    12,
    0,
    13,
    14,
    15,
    16,
    17,
    0,
    0,
    0,
    0,
    18,
    0,
    0,
    0,
    0,
    19,
    0,
    0,
    0,
    0,
    20,
    0,
    0,
    0,
    21,
    0,
    0,
    0,
    22,
    0,
    0,
    0,
    0,
    0,
    23,
    0,
    0,
    0,
    24,
    0,
    0,
    0,
    0,
    25,
    0,
    0,
    0,
    0,
    0,
    0,
    0,
    26,
    27,
    0,
    0,
    0,
    28,
    0,
    0,
    0,
    0,
    0,
    0,
    0,
    0,
    29,
    0,
    0,
    0,
    30,
    0,
    0,
    0,
    0,
    31,
    0,
    0,
    0,
    0,
    0,
    0,
    32,
    33,
    34,
    0,
    0,
    0,
    35,
    0,
    0,
    0,
    0,
    36,
    0,
    0,
    0,
    0,
    37,
    38,
    39,
    40,
    0,
    0,
    0,
    0,
    41,
    0,
    0,
    0,
    0,
    42,
    0,
    0,
    0,
    0,
    0,
    43,
    0,
    0,
    44,
    0,
    0,
    0,
    45,
    0,
    0,
    0,
    0,
    46,
    0,
    0,
    0,
    0,
    0,
    47,
    0,
    0,
    0,
    48,
    0,
    0,
    49,
    0,
    0,
    0,
    0,
    50,
    0,
    0,
    0,
    0,
    0,
    51,
    0,
    0,
    0,
    0,
    0,
    0,
    52,
    0,
    0,
    0,
    0,
    53,
    0,
    0,
    0,
    0,
    0,
    54,
    0,
    0,
    0,
    0,
    0,
    55,
    56,
    0,
    0,
    0,
    0,
    57,
    0,
    0,
    0,
    0,
    0,
    58,
    0,
    0,
    0,
    0,
    59,
    60,
    61,
    0,
    0,
    0,
    0,
    62,
    0,
    0,
    0,
    0,
    0,
    63,
    0,
    0,
    0,
    0,
    64,
    0,
    0,
    65,
    0,
    0,
    0,
    66,
    0,
    0,
    0,
    0,
    0,
    67,
    0,
    0,
    0,
    0,
    68,
    0,
    0,
    0,
    69,
    0,
    0,
    70,
    0,
    0,
    0,
    0,
    0,
    71,
    0,
    0,
    0,
    0,
    72,
    0,
    0,
    0,
    0,
    0,
    0,
    0,
    73,
    0,
    0,
    0,
    0,
    74,
    0,
    0,
    0,
    0,
    75,
    0,
    0,
    0,
    0,
    0,
    76,
    77,
    78,
    0,
    0,
    0,
    0,
    79,
    0,
    0,
    0,
    0,
    80,
    0,
    0,
    0,
    81,
    82,
    83,
    84,
    0,
    0,
    0,
    0,
    0,
    85,
    0,
    0,
    0,
    86,
    87,
    0,
    0,
    0,
    0,
    0,
    0,
    0,
    88,
    0,
    0,
    0,
    0,
    89,
    0,
    0,
    0,
    0,
    90,
    0,
    0,
    0,
    0,
    91,
    0,
    0,
    0,
    92,
    0,
    0,
    0,
    0,
    93,
    0,
    0,
    0,
    0,
    94,
    0,
    0,
    0,
    0,
    95,
    0,
    0,
    0
  ],
  "gridSize": { "columns": 19, "rows": 19 }
}
